CHANGES.txt
LICENSE.txt
MANIFEST.in
README.txt
setup.py
CombiVEP.egg-info/PKG-INFO
CombiVEP.egg-info/SOURCES.txt
CombiVEP.egg-info/dependency_links.txt
CombiVEP.egg-info/requires.txt
CombiVEP.egg-info/top_level.txt
bin/CombiVEP_predictor
bin/CombiVEP_reference_updater
bin/CombiVEP_trainer
combivep/__init__.py
combivep/app.py
combivep/cfg.py
combivep/settings.py
combivep/template.py
combivep/data/CBV/test.cbv
combivep/data/CBV/training.cbv
combivep/engine/__init__.py
combivep/engine/dataset.py
combivep/engine/mlp.py
combivep/engine/wrapper.py
combivep/preproc/__init__.py
combivep/preproc/dataset.py
combivep/preproc/reader.py
combivep/preproc/referer.py
combivep/refdb/__init__.py
combivep/refdb/control.py
combivep/refdb/updater.py