Metadata-Version: 1.0
Name: CombiVEP
Version: 0.1.2
Summary: Combined Variant Effect Predictors
Home-page: http://pypi.python.org/pypi/CombiVEP/
Author: Jessada Thutkawkorapin
Author-email: jessada115@hotmail.com
License: LICENSE.txt
Platform: UNKNOWN
